localtalk/__init__.py
localtalk/assets/banner.txt
localtalk/cli.py
localtalk/core/__init__.py
localtalk/core/assistant.py
localtalk/models/__init__.py
localtalk/models/config.py
localtalk/services/__init__.py
localtalk/services/audio.py
localtalk/services/audio_vad_auto.py
localtalk/services/mlx_llm.py
localtalk/services/mlx_tts.py
localtalk/services/speech_recognition.py
localtalk/services/speech_recognition_fast.py
localtalk/utils/__init__.py
localtalk/utils/emotion.py
localtalk/utils/mlx_compat.py
localtalk/utils/text_processing.py
localtalk-0.3.0.dist-info/WHEEL
localtalk-0.3.0.dist-info/entry_points.txt
localtalk-0.3.0.dist-info/METADATA
localtalk-0.3.0.dist-info/RECORD
