Metadata-Version: 2.4
Name: localtalk
Version: 0.3.0
Summary: A local/offline-capable voice assistant with speech recognition, LLM processing, and text-to-speech
Keywords: apple-silicon,llm,local,offline,privacy,speech-recognition,tts,voice-assistant
Author: Anthony Wu
Author-email: Anthony Wu <pls-file-gh-issue@users.noreply.github.com>
License-Expression: MIT
Classifier: Development Status :: 3 - Alpha
Classifier: Intended Audience :: Developers
Classifier: License :: OSI Approved :: MIT License
Classifier: Operating System :: MacOS
Classifier: Operating System :: MacOS :: MacOS X
Classifier: Programming Language :: Python :: 3
Classifier: Programming Language :: Python :: 3.11
Classifier: Programming Language :: Python :: 3.12
Classifier: Programming Language :: Python :: 3.13
Classifier: Programming Language :: Python :: 3 :: Only
Classifier: Topic :: Software Development :: Libraries :: Python Modules
Classifier: Topic :: Multimedia :: Sound/Audio :: Speech
Classifier: Environment :: MacOS X
Requires-Dist: einops>=0.8.0
Requires-Dist: hf-transfer>=0.1.9
Requires-Dist: huggingface-hub>=0.36.0,<1.0
Requires-Dist: librosa>=0.11.0
Requires-Dist: mistune>=3.2.0,<4.0
Requires-Dist: mlx>=0.30.1
Requires-Dist: mlx-audio>=0.2.9
Requires-Dist: mlx-lm>=0.29.1
Requires-Dist: mlx-vlm>=0.3.9
Requires-Dist: numpy>=2.0,<2.3.0
Requires-Dist: onnxruntime>=1.16.1
Requires-Dist: openai-harmony>=0.0.8,<1.0
Requires-Dist: openai-whisper>=20250625
Requires-Dist: pydantic>=2.0.0
Requires-Dist: rich>=14.2.0
Requires-Dist: silero-vad>=6.2
Requires-Dist: sounddevice>=0.5
Requires-Dist: soundfile>=0.13
Requires-Dist: torch>=2.7.0
Requires-Dist: torchaudio>=2.7.0
Requires-Dist: transformers>=4.54.0
Requires-Dist: pytest>=8.4.0 ; extra == 'dev'
Requires-Dist: pytest-asyncio>=0.23.0 ; extra == 'dev'
Requires-Dist: pytest-cov>=5.0.0 ; extra == 'dev'
Requires-Dist: ruff>=0.14.10 ; extra == 'dev'
Requires-Python: >=3.11
Project-URL: Documentation, https://github.com/anthonywu/localtalk#readme
Project-URL: Homepage, https://github.com/anthonywu/localtalk
Project-URL: Issues, https://github.com/anthonywu/localtalk/issues
Project-URL: Repository, https://github.com/anthonywu/localtalk.git
Provides-Extra: dev
